openeo_driver/ProcessGraphDeserializer.py
openeo_driver/__init__.py
openeo_driver/_version.py
openeo_driver/asset_urls.py
openeo_driver/backend.py
openeo_driver/constants.py
openeo_driver/datacube.py
openeo_driver/datastructs.py
openeo_driver/delayed_vector.py
openeo_driver/dry_run.py
openeo_driver/errors.py
openeo_driver/filter_properties.py
openeo_driver/jobregistry.py
openeo_driver/processes.py
openeo_driver/processgraph.py
openeo_driver/save_result.py
openeo_driver/server.py
openeo_driver/testing.py
openeo_driver/urlsigning.py
openeo_driver/utils.py
openeo_driver/views.py
openeo_driver/workspace.py
openeo_driver/workspacerepository.py
openeo_driver/config/__init__.py
openeo_driver/config/base.py
openeo_driver/config/config.py
openeo_driver/config/default.py
openeo_driver/config/env.py
openeo_driver/config/load.py
openeo_driver/config/integrations/__init__.py
openeo_driver/config/integrations/s3_config.py
openeo_driver/dummy/__init__.py
openeo_driver/dummy/dummy_backend.py
openeo_driver/dummy/dummy_config.py
openeo_driver/dummy/local_app.py
openeo_driver/integrations/__init__.py
openeo_driver/integrations/s3/__init__.py
openeo_driver/integrations/s3/bucket_details.py
openeo_driver/integrations/s3/client.py
openeo_driver/integrations/s3/credentials.py
openeo_driver/integrations/s3/presigned_url.py
openeo_driver/specs/__init__.py
openeo_driver/specs/openeo-api/0.4/CHANGELOG.md
openeo_driver/specs/openeo-api/0.4/LICENSE
openeo_driver/specs/openeo-api/0.4/README.md
openeo_driver/specs/openeo-api/0.4/errors.json
openeo_driver/specs/openeo-api/0.4/openapi.json
openeo_driver/specs/openeo-api/0.4/subscriptions.json
openeo_driver/specs/openeo-api/1.x/CHANGELOG.md
openeo_driver/specs/openeo-api/1.x/LICENSE
openeo_driver/specs/openeo-api/1.x/README.md
openeo_driver/specs/openeo-api/1.x/errors.json
openeo_driver/specs/openeo-api/1.x/package.json
openeo_driver/specs/openeo-processes/1.x/CHANGELOG.md
openeo_driver/specs/openeo-processes/1.x/LICENSE
openeo_driver-0.136.0a4.dist-info/licenses/LICENSE
openeo_driver-0.136.0a4.dist-info/METADATA
openeo_driver-0.136.0a4.dist-info/WHEEL
openeo_driver-0.136.0a4.dist-info/top_level.txt
openeo_driver-0.136.0a4.dist-info/RECORD
