Metadata-Version: 2.4
Name: openeo_driver
Version: 0.136.0a4
Summary: Flask based frontend for openEO API implementations in Python.
Home-page: https://github.com/Open-EO/openeo-python-driver
Author: Jeroen Dries
Author-email: jeroen.dries@vito.be
Classifier: Programming Language :: Python :: 3
Classifier: License :: OSI Approved :: Apache Software License
Classifier: Development Status :: 4 - Beta
Classifier: Operating System :: OS Independent
Requires-Python: >=3.8
License-File: LICENSE
Requires-Dist: flask>=2.0.0
Requires-Dist: werkzeug>=3.0.3
Requires-Dist: requests>=2.28.0
Requires-Dist: openeo>=0.46.0.a2.dev
Requires-Dist: openeo_processes==0.0.4
Requires-Dist: gunicorn>=20.0.1
Requires-Dist: numpy>=1.22.0
Requires-Dist: shapely>=1.8.5
Requires-Dist: pandas>=1.4.0
Requires-Dist: geopandas>=0.11.0
Requires-Dist: xarray>=0.16.2
Requires-Dist: flask-cors
Requires-Dist: pyproj>=2.1.0
Requires-Dist: python-dateutil
Requires-Dist: python-json-logger~=2.0
Requires-Dist: deprecated>=1.2.12
Requires-Dist: importlib_resources; python_version < "3.10"
Requires-Dist: attrs>=23.1.0
Requires-Dist: fiona>=1.9.0
Requires-Dist: fiona<1.10.0; python_version < "3.9"
Requires-Dist: reretry~=0.11.8
Requires-Dist: markdown>3.4
Requires-Dist: traceback-with-variables==2.0.4
Requires-Dist: pystac~=1.8.0
Provides-Extra: dev
Requires-Dist: pytest; extra == "dev"
Requires-Dist: mock; extra == "dev"
Requires-Dist: requests-mock; extra == "dev"
Requires-Dist: pylint>=2.5.0; extra == "dev"
Requires-Dist: astroid>=2.4.0; extra == "dev"
Requires-Dist: openeo_udf>=1.0.0rc3; extra == "dev"
Requires-Dist: boto3[s3]>=1.26.17; extra == "dev"
Requires-Dist: moto[s3]>=5.0.0; extra == "dev"
Requires-Dist: time-machine>=2.8.0; extra == "dev"
Requires-Dist: netCDF4>=1.5.4; extra == "dev"
Requires-Dist: re-assert; extra == "dev"
Requires-Dist: pyarrow>=10.0.0; extra == "dev"
Requires-Dist: pystac; extra == "dev"
Requires-Dist: jsonschema; extra == "dev"
Requires-Dist: dirty-equals>=0.6; extra == "dev"
Requires-Dist: mypy-boto3-s3; extra == "dev"
Provides-Extra: s3
Requires-Dist: boto3[s3]>=1.26.17; extra == "s3"
Requires-Dist: botocore; extra == "s3"
Provides-Extra: vault
Requires-Dist: hvac>=1.0.2; extra == "vault"
Dynamic: author
Dynamic: author-email
Dynamic: classifier
Dynamic: description
Dynamic: home-page
Dynamic: license-file
Dynamic: provides-extra
Dynamic: requires-dist
Dynamic: requires-python
Dynamic: summary
